pyfaze
