Metadata-Version: 1.0
Name: pyfaze
Version: 0.1.3dev
Summary: Communication library for Anafaze/Watlow thermal controllers
Home-page: https://github.com/gregjurman/pyfaze
Author: Greg Jurman
Author-email: gdj2214@rit.edu
License: MIT
Keywords: anafaze watlow serial temp industrial
Platform: UNKNOWN
